Phanatic/__init__.py
Phanatic/check.py
Phanatic/main.py
Phanatic-2.2.4.data/data/LICENSE.md
Phanatic-2.2.4.dist-info/LICENSE.md
Phanatic-2.2.4.dist-info/METADATA
Phanatic-2.2.4.dist-info/WHEEL
Phanatic-2.2.4.dist-info/entry_points.txt
Phanatic-2.2.4.dist-info/top_level.txt
Phanatic-2.2.4.dist-info/RECORD
